.gitignore
README.md
__init__.py
conftest.py
pytest.ini
setup.py
zops/__init__.py
zops.anatomy.egg-info/PKG-INFO
zops.anatomy.egg-info/SOURCES.txt
zops.anatomy.egg-info/dependency_links.txt
zops.anatomy.egg-info/entry_points.txt
zops.anatomy.egg-info/namespace_packages.txt
zops.anatomy.egg-info/requires.txt
zops.anatomy.egg-info/top_level.txt
zops/anatomy/__init__.py
zops/anatomy/assertions.py
zops/anatomy/cli.py
zops/anatomy/_tests/test_anatomy.py
zops/anatomy/layers/__init__.py
zops/anatomy/layers/feature.py
zops/anatomy/layers/playbook.py
zops/anatomy/layers/tree.py
zops/anatomy/layers/_tests/test_feature.py
zops/anatomy/layers/_tests/test_tree.py