Metadata-Version: 1.1
Name: zops.anatomy
Version: 3.7.0
Summary: Apply and maintain projects templates.
Home-page: https://github.com/zerotk/zops.anatomy
Author: Alexandre Andrade
Author-email: kaniabi@gmail.com
License: MIT license
Keywords: development environment,shell,operations
Platform: UNKNOWN
Classifier: Development Status :: 2 - Pre-Alpha
Classifier: Intended Audience :: Developers
Classifier: License :: OSI Approved :: MIT License
Classifier: Natural Language :: English
Classifier: Programming Language :: Python :: 2
Classifier: Programming Language :: Python :: 2.7
Classifier: Programming Language :: Python :: 3
Classifier: Programming Language :: Python :: 3.5
